iamapackage/__init__.py
iamapackage/_git_version.py
iamapackage/_version.py
iamapackage/getting_started.py
iamapackage-1.0.0.dist-info/LICENSE
iamapackage-1.0.0.dist-info/METADATA
iamapackage-1.0.0.dist-info/WHEEL
iamapackage-1.0.0.dist-info/top_level.txt
iamapackage-1.0.0.dist-info/RECORD
